thermostat/__init__.py
thermostat/dataset.py
thermostat/explain.py
thermostat/utils.py
thermostat/visualize.py
thermostat/data/__init__.py
thermostat/data/additional_configs.py
thermostat/data/dataset_utils.py
thermostat/data/readers.py
thermostat/data/stats.py
thermostat/data/thermostat_configs.py
thermostat/data/tokenization.py
thermostat/explainers/__init__.py
thermostat/explainers/grad.py
thermostat/explainers/iba.py
thermostat/explainers/lime.py
thermostat/explainers/occlusion.py
thermostat/explainers/shap.py
thermostat/explainers/svs.py
thermostat_datasets-1.1.0.dist-info/LICENSE
thermostat_datasets-1.1.0.dist-info/METADATA
thermostat_datasets-1.1.0.dist-info/WHEEL
thermostat_datasets-1.1.0.dist-info/top_level.txt
thermostat_datasets-1.1.0.dist-info/RECORD
